port43/__init__.py
port43/core/__init__.py
port43/core/dns.py
port43/core/rdap.py
port43/core/whois.py
port43/prompts/__init__.py
port43/prompts/react_json_tools.py
port43/prompts/whois_text_to_json.py
port43/tools/__init__.py
port43/tools/dns.py
port43/tools/rdap.py
port43/tools/whois.py
port43-0.1.dev0.dist-info/METADATA
port43-0.1.dev0.dist-info/WHEEL
port43-0.1.dev0.dist-info/licenses/LICENSE
port43-0.1.dev0.dist-info/RECORD
