Metadata-Version: 2.1
Name: port43
Version: 0.1.dev0
Summary: A set of open-source Information Security tools for the 🦜🔗 LangChain framework
Project-URL: Homepage, https://github.com/pogzyb/port43
Project-URL: Issues, https://github.com/pogzyb/port43/issues
Author-email: pogzyb <pogzyb@umich.edu>
License:                                  Apache License
License-File: LICENSE
Classifier: License :: OSI Approved :: MIT License
Classifier: Operating System :: OS Independent
Classifier: Programming Language :: Python :: 3
Requires-Python: >=3.9
Requires-Dist: asyncwhois
Requires-Dist: langchain
